<?xml version="1.0" encoding="UTF-8" ?>
<!DOCTYPE mapper PUBLIC "-//mybatis.org//DTD Mapper 3.0//EN" "http://mybatis.org/dtd/mybatis-3-mapper.dtd" >
<mapper namespace="mapper.CommentMapperCustom">
	<resultMap id="CommentResultMap" type="po.CommentCustom">
		<id column="comment_id" property="commentId" jdbcType="INTEGER" />
		<result column="user_id" property="userId" jdbcType="INTEGER" />
		<result column="weibo_id" property="weiboId" jdbcType="INTEGER" />
		<result column="comment_time" property="commentTime" jdbcType="TIMESTAMP" />
		<result column="comment_content" property="commentContent" jdbcType="VARCHAR" />
		<result column="face" property="user.face"/>
		<result column="nickname" property="user.nickname"/>
		
		<association property="user" javaType="po.User">
			<id column="user_id" property="userId" jdbcType="INTEGER" />
			<result column="username" property="username" jdbcType="VARCHAR" />
			<result column="password" property="password" jdbcType="VARCHAR" />
			<result column="nickname" property="nickname" jdbcType="VARCHAR" />
			<result column="face" property="face" jdbcType="VARCHAR" />
			<result column="sex" property="sex" jdbcType="INTEGER" />
			<result column="bir" property="bir" jdbcType="DATE" />
			<result column="province" property="province" jdbcType="VARCHAR" />
			<result column="city" property="city" jdbcType="VARCHAR" />
		</association>
		<association property="weibo" javaType="po.Weibo">
			<id column="weibo_id" property="weiboId" jdbcType="INTEGER" />
			<result column="user_id" property="userId" jdbcType="INTEGER" />
			<result column="post_time" property="postTime" jdbcType="TIMESTAMP" />
			<result column="content" property="content" jdbcType="VARCHAR" />
			<result column="original" property="original" jdbcType="INTEGER" />
	    	<result column="repost_id" property="repostId" jdbcType="INTEGER" />
		</association>
	</resultMap>

	<!-- 添加评论 -->
	<insert id="addComment" parameterType="po.CommentCustom" keyProperty="comment_id" useGeneratedKeys="true">
		insert into comment (user_id, weibo_id, comment_time, comment_content) 
		VALUE(#{userId},#{weiboId},#{commentTime},#{commentContent})
	</insert>

	<!-- 查询微博Id的评论 -->
	<select id="queryComment" parameterType="int" resultMap="CommentResultMap">
		SELECT b.user_id,a.face,b.comment_id,a.face,b.comment_content,b.comment_time,a.nickname 
		FROM USER AS a , COMMENT AS b
		WHERE a.user_id=b.user_id AND b.weibo_id=#{weiboId}
	</select>

	<!-- 查询评论回复数 -->
	<select id="qeuryCountReply" parameterType="int" resultType="int">
		SELECT COUNT(*) FROM reply AS a WHERE a.comment_id=#{commentId}
	</select>

	<!-- 删除评论 -->
	<delete id="deleteCommentById" parameterType="int">
		DELETE FROM COMMENT WHERE comment_id = #{commentId}
	</delete>
	
	<!-- 根据userID查询评论列表 -->
	<select id="queryCommentByUserId" parameterType="int" resultMap="CommentResultMap">
		SELECT u.nickname,u.face,c.*,w.user_id, wu.nickname AS weibo_nickname, w.post_time, w.content
		FROM COMMENT AS c,USER AS u, weibo AS w, USER AS wu
		WHERE u.user_id=c.user_id 
		AND w.weibo_id=c.weibo_id 
		AND wu.user_id=w.user_id 
		AND w.user_id=#{params.userId} 
		ORDER BY c.comment_time DESC
	</select>
	
	
</mapper>